couragesteak_python_sdk_demo/__init__.py
couragesteak_python_sdk_demo/__version__.py
couragesteak_python_sdk_demo/app.py
couragesteak_python_sdk_demo/base/__init__.py
couragesteak_python_sdk_demo/util/__init__.py
couragesteak_python_sdk_demo/util/util_math.py
couragesteak_python_sdk_demo/util/util_string.py
couragesteak_python_sdk_demo-0.0.2.dist-info/METADATA
couragesteak_python_sdk_demo-0.0.2.dist-info/WHEEL
couragesteak_python_sdk_demo-0.0.2.dist-info/top_level.txt
couragesteak_python_sdk_demo-0.0.2.dist-info/RECORD
