Metadata-Version: 2.1
Name: couragesteak-python-sdk-demo
Version: 0.0.2
Summary: 这是项目描述（简短版）
Home-page: https://www.couragesteak.com/
Author: 有勇气的牛排
Author-email: warm7758@163.com
License: UNKNOWN
Keywords: python,menu,dumb_menu,windows,mac,linux
Platform: UNKNOWN
Classifier: Development Status :: 1 - Planning
Classifier: Intended Audience :: Developers
Classifier: Programming Language :: Python :: 3
Classifier: Operating System :: Unix
Classifier: Operating System :: MacOS :: MacOS X
Classifier: Operating System :: Microsoft :: Windows
